sculptor/__init__.py
sculptor/sculptor.py
sculptor/sculptor_pipeline.py
sculptor/utils.py
sculptor-0.2.0.dist-info/licenses/LICENSE
sculptor-0.2.0.dist-info/METADATA
sculptor-0.2.0.dist-info/WHEEL
sculptor-0.2.0.dist-info/top_level.txt
sculptor-0.2.0.dist-info/RECORD
