Metadata-Version: 2.4
Name: sculptor
Version: 0.2.0
Summary: Sculptor: Structuring unstructured data with LLMs
Author-email: Ben Turtel <ben@lightningrod.ai>
License: Copyright 2025 Junto Tech, Inc. dba Lightning Rod Labs
Project-URL: Homepage, https://lightningrod.ai
Project-URL: Source, https://github.com/lightning-rod-labs/sculptor
Project-URL: Repository, https://github.com/lightning-rod-labs/sculptor.git
Keywords: data sculpting,llm,large language model,unstructured data,structured data,data extraction,information extraction,data transformation,text processing,natural language processing,nlp,pipeline,text to structured data
Classifier: Development Status :: 3 - Alpha
Classifier: Intended Audience :: Developers
Classifier: License :: OSI Approved :: MIT License
Classifier: Topic :: Software Development :: Libraries
Classifier: Topic :: Software Development :: Libraries :: Python Modules
Classifier: Topic :: Text Processing :: Linguistic
Classifier: Topic :: Scientific/Engineering :: Artificial Intelligence
Classifier: Topic :: Scientific/Engineering :: Information Analysis
Classifier: Programming Language :: Python :: 3
Classifier: Programming Language :: Python :: 3.8
Classifier: Programming Language :: Python :: 3.9
Classifier: Programming Language :: Python :: 3.10
Classifier: Typing :: Typed
Requires-Python: >=3.7
License-File: LICENSE
Requires-Dist: openai>=0.27.0
Requires-Dist: tqdm>=4.0
Requires-Dist: PyYAML>=6.0
Requires-Dist: asgiref>=3.0
Dynamic: license-file
